test/__init__.py
test/conftest.py
test/test_config.py
test/test_files.py
test/test_wf.py
test/unit/__init__.py
test/unit/test_column_find.py
test/unit/test_datetime_format_util.py
test/unit/test_replace_translation.py
test/unit/test_tf_alias_naming_util.py
trifacta/__init__.py
trifacta/client.py
trifacta/constants.py
trifacta/main.py
trifacta/version.py
trifacta/tfobjects/__init__.py
trifacta/tfobjects/hello.py
trifacta/tfobjects/wrangle_flow.py
trifacta/transform_functions/__init__.py
trifacta/transform_functions/function_definitions.py
trifacta/transform_functions/quote_matcher.py
trifacta/util/__init__.py
trifacta/util/datetime_formatting_util.py
trifacta/util/tfAPIs.py
trifacta/util/tf_alias_naming_util.py
trifacta/util/tfconfig.py
trifacta/util/tffiles.py
trifacta/util/tfrequests.py
trifacta-8.5.1.dist-info/LICENSE.txt
trifacta-8.5.1.dist-info/METADATA
trifacta-8.5.1.dist-info/WHEEL
trifacta-8.5.1.dist-info/top_level.txt
trifacta-8.5.1.dist-info/RECORD
