Metadata-Version: 2.1
Name: trifacta
Version: 8.5.1
Summary: Python SDK for Trifacta
Home-page: https://www.trifacta.com
Author: Trifacta Inc
Author-email: support@trifacta.com
License: UNKNOWN
Keywords: dataprep preparation wrangle wrangling wrangler trifacta
Platform: UNKNOWN
Requires-Python: >3.6, < 3.9
License-File: LICENSE.txt
Requires-Dist: pandas (>=1.1.2)
Requires-Dist: numpy (>=1.17.0)
Requires-Dist: requests (>=2.22.0)
Requires-Dist: regex (>=2020.10.11)
Requires-Dist: python-slugify (>=4.0.1)
Requires-Dist: tqdm (>=4.55.1)
Requires-Dist: boto3 (>=1.17.25)
Requires-Dist: ipywidgets (>=7.6.3)
Requires-Dist: ijson (>=3.1.4)
Requires-Dist: simplejson (>=3.16.0)
Requires-Dist: pywebhdfs (>=0.4.1)
Requires-Dist: metaphone (>=0.6)
